rapconector/__init__.py
rapconector/client.py
rapconector/document.py
rapconector/errors.py
rapconector/session.py
rapconector/utils.py
rapconector/version.py
rap_conector_client-0.25.0.2.dist-info/LICENSE.md
rap_conector_client-0.25.0.2.dist-info/METADATA
rap_conector_client-0.25.0.2.dist-info/WHEEL
rap_conector_client-0.25.0.2.dist-info/top_level.txt
rap_conector_client-0.25.0.2.dist-info/RECORD
