Metadata-Version: 2.1
Name: rap-conector-client
Version: 0.25.0.2
Summary: Client for interacting with a RAP Conector API instance
Author: Samuel de Moura
Author-email: samueldemouramoreira@gmail.com
License: LGPLv3
Classifier: Development Status :: 5 - Production/Stable
Classifier: Intended Audience :: Developers
Classifier: License :: OSI Approved :: GNU Lesser General Public License v3 (LGPLv3)
Classifier: Natural Language :: Portuguese (Brazilian)
Classifier: Programming Language :: Python :: 2
Classifier: Programming Language :: Python :: 2.7
Classifier: Programming Language :: Python :: 3
Classifier: Programming Language :: Python :: 3.5
Classifier: Programming Language :: Python :: 3.6
Classifier: Programming Language :: Python :: 3.7
Classifier: Programming Language :: Python :: 3.8
Classifier: Programming Language :: Python :: 3.9
Classifier: Programming Language :: Python :: 3.10
Classifier: Programming Language :: Python :: 3.11
Classifier: Programming Language :: Python :: 3.12
License-File: LICENSE.md
Requires-Dist: requests
Requires-Dist: requests-toolbelt
Provides-Extra: dev
Requires-Dist: yapf ; extra == 'dev'
Requires-Dist: pylint ; extra == 'dev'
Provides-Extra: docs
Requires-Dist: sphinx ; extra == 'docs'
Requires-Dist: sphinx-rtd-theme ; extra == 'docs'
Provides-Extra: publish
Requires-Dist: twine ; extra == 'publish'
Provides-Extra: test
Requires-Dist: tox <4 ; extra == 'test'
Requires-Dist: pytest ; extra == 'test'
Requires-Dist: pytest-cov ; extra == 'test'
Requires-Dist: responses ; extra == 'test'
